magi_dataset/__init__.py
magi_dataset/__main__.py
magi_dataset/magi_dataset.py
magi_dataset/data/__init__.py
magi_dataset/data/patterns.txt
magi_dataset-1.0.9.dist-info/METADATA
magi_dataset-1.0.9.dist-info/WHEEL
magi_dataset-1.0.9.dist-info/entry_points.txt
magi_dataset-1.0.9.dist-info/top_level.txt
magi_dataset-1.0.9.dist-info/RECORD
