Metadata-Version: 2.1
Name: magi-dataset
Version: 1.0.9
Summary: Convenient access to massive corpus of GitHub repositories
Home-page: https://github.com/Enoch2090/magi_dataset
Author: Enoch2090
Author-email: ycgu2090@gmail.com
License: GPLv3
Platform: UNKNOWN
Classifier: License :: OSI Approved :: GNU General Public License v3 (GPLv3)
Classifier: Programming Language :: Python
Classifier: Programming Language :: Python :: 3
Classifier: Programming Language :: Python :: 3.6
Classifier: Programming Language :: Python :: Implementation :: CPython
Classifier: Programming Language :: Python :: Implementation :: PyPy
Requires-Python: >=3.7.0
Requires-Dist: Markdown
Requires-Dist: PyGithub
Requires-Dist: beautifulsoup4
Requires-Dist: deep-translator
Requires-Dist: hn
Requires-Dist: langdetect
Requires-Dist: lxml
Requires-Dist: networkx
Requires-Dist: numpy (>=1.15.4)
Requires-Dist: pandas (>=1.2.0)
Requires-Dist: python-hn
Requires-Dist: requests
Requires-Dist: scipy
Requires-Dist: setuptools
Requires-Dist: spacy
Requires-Dist: tqdm
Provides-Extra: elasticsearch
Requires-Dist: elasticsearch ; extra == 'elasticsearch'
